seq_multiplier.v
module seq_multiplier #(
    parameter WIDTH = 8
)(
    input  wire                        clk,
    input  wire                        rst,
    input  wire                        start,
    input  wire signed [WIDTH-1:0]     ip_A,
    input  wire signed [WIDTH-1:0]     ip_B,

    output reg  signed [2*WIDTH-1:0]   product,
    output reg                         done
);

//stage encoding

localparam IDLE  = 3'd0,
           LOAD  = 3'd1,
           CHECK = 3'd2,
           ADD   = 3'd3,
           SHIFT = 3'd4,
           COUNT = 3'd5,
           DONE  = 3'd6;

reg [2:0] state, next_state;

// Datapath Registers

reg sign;

reg [WIDTH:0] A;
reg [WIDTH:0] M;
reg [WIDTH-1:0] Q;
reg C;

localparam COUNT_W = $clog2(WIDTH);
reg [COUNT_W:0] counter;

// Control Signals

reg load_en;
reg add_en;
reg shift_en;
reg count_en;

// Output Logic

always @(*) begin

    load_en  = 1'b0;
    add_en   = 1'b0;
    shift_en = 1'b0;
    count_en = 1'b0;
    done     = 1'b0;

    case(state)

        LOAD  : load_en  = 1'b1;
        ADD   : add_en   = 1'b1;
        SHIFT : shift_en = 1'b1;
        COUNT : count_en = 1'b1;
        DONE  : done     = 1'b1;

        default: ;

    endcase

end

// Next State Logic

always @(*) begin

    next_state = state;

    case(state)

        IDLE:
            if(start)
                next_state = LOAD;

        LOAD:
            next_state = CHECK;

        CHECK:
            if(Q[0])
                next_state = ADD;
            else
                next_state = SHIFT;

        ADD:
            next_state = SHIFT;

        SHIFT:
            next_state = COUNT;

        COUNT:
            if(counter == WIDTH-1)
                next_state = DONE;
            else
                next_state = CHECK;

        DONE:
            next_state = IDLE;

        default:
            next_state = IDLE;

    endcase

end

// Datapath

always @(posedge clk) begin

    if(rst) begin

        A       <= '0;
        M       <= '0;
        Q       <= '0;
        C       <= 1'b0;
        sign    <= 1'b0;
        counter <= '0;
        product <= '0;

    end
    else begin

        if(load_en) begin

            sign <= ip_A[WIDTH-1] ^ ip_B[WIDTH-1];

            M <= ip_A[WIDTH-1] ? {1'b0,(~ip_A + 1'b1)} : {1'b0,ip_A};
            Q <= ip_B[WIDTH-1] ? (~ip_B + 1'b1) : ip_B;

            A <= '0;
            C <= 1'b0;

            counter <= '0;
            product <= '0;

        end

        else if(add_en) begin

            {C,A} <= {1'b0,A} + {1'b0,M};

        end

        else if(shift_en) begin

            {C,A,Q} <= {C,A,Q} >> 1;

        end

        else if(count_en) begin

            if(counter == WIDTH-1) begin

                if(sign)
                    product <= -$signed({A[WIDTH-1:0],Q});
                else
                    product <=  $signed({A[WIDTH-1:0],Q});

            end

            counter <= counter + 1'b1;

        end

    end

end

// State Register

always @(posedge clk) begin

    if(rst)
        state <= IDLE;
    else
        state <= next_state;

end

endmodule

tb.v
`timescale 1ns/1ps

module tb;

parameter WIDTH = 8;

reg clk;
reg rst;
reg start;

reg  signed [WIDTH-1:0] ip_A;
reg  signed [WIDTH-1:0] ip_B;

wire signed [2*WIDTH-1:0] product;
wire done;

//--------------------------------------------------
// DUT
//--------------------------------------------------
integer acc_toggles = 0;

reg [WIDTH:0] prev_A;

seq_multiplier #(
    .WIDTH(WIDTH)
) dut (
    .clk(clk),
    .rst(rst),
    .start(start),
    .ip_A(ip_A),
    .ip_B(ip_B),
    .product(product),
    .done(done)
);

//--------------------------------------------------
// Clock
//--------------------------------------------------

initial begin
    clk = 0;
    forever #5 clk = ~clk;
end

//--------------------------------------------------
// Statistics
//--------------------------------------------------

integer pass_count = 0;
integer fail_count = 0;

reg signed [2*WIDTH-1:0] expected;

//--------------------------------------------------
// Test Task
//--------------------------------------------------

task run_test;

    input signed [WIDTH-1:0] a;
    input signed [WIDTH-1:0] b;

    begin

        expected = a * b;

        @(posedge clk);
        ip_A  <= a;
        ip_B  <= b;
        start <= 1'b1;

        @(posedge clk);
        start <= 1'b0;

        wait(done);

        @(posedge clk);

        $display("------------------------------------------------------------");
        $display("A = %4d   B = %4d", a, b);
        $display("Expected = %6d", expected);
        $display("Obtained = %6d", product);

        if(product === expected) begin
            pass_count = pass_count + 1;
            $display("STATUS : PASS");
        end
        else begin
            fail_count = fail_count + 1;
            $display("STATUS : FAIL");
        end

    end

endtask

//--------------------------------------------------
// Test Sequence
//--------------------------------------------------

initial begin

    rst   = 1'b1;
    start = 1'b0;
    ip_A  = '0;
    ip_B  = '0;

    prev_A = '0;
    acc_toggles = 0;

    repeat(2) @(posedge clk);

    rst = 1'b0;

    // Basic functionality
    run_test(10, 5);
    run_test(7, 3);
    run_test(25, 4);

    // Zero cases
    run_test(0, 25);
    run_test(25, 0);
    run_test(0, 0);

    // Positive × Negative
    run_test(12, -5);
    run_test(-8, 7);

    // Negative × Negative
    run_test(-10, -9);
    run_test(-5, -1);

    // Boundary values
    run_test(127, 1);
    run_test(-128, 1);
    run_test(127, -1);
    run_test(-128, -1);

    // Extreme products
    run_test(127, 127);
    run_test(-128, -128);
    run_test(-128, 127);
    run_test(127, -128);

    //--------------------------------------------------

    $display("\n============================================================");
    $display("Simulation Summary");
    $display("------------------------------------------------------------");
    $display("Tests Passed : %0d", pass_count);
    $display("Tests Failed : %0d", fail_count);

    if(fail_count == 0)
        $display("RESULT : ALL TESTS PASSED");
    else
        $display("RESULT : TEST FAILED");

    $display("============================================================");

    #20;
    $finish;

end

//--------------------------------------------------
// Uncomment for debugging
//--------------------------------------------------
/*
initial begin
    $display("time state A M Q Q_1 count product done");

    $monitor("%4t %2d %4h %4h %4h %b %2d %6h %b",
        $time,
        dut.state,
        dut.A,
        dut.M,
        dut.Q,
        dut.Q_1,
        dut.counter,
        product,
        done);
end
*/

//--------------------------------------------------
// Waveforms
//--------------------------------------------------

initial begin
    $dumpfile("booth_multiplier.vcd");
    $dumpvars(0, tb);
end

endmodule

booth_multiplier.vcd
$date
	Mon Jun 29 17:50:50 2026
$end
$version
	Icarus Verilog
$end
$timescale
	1ps
$end
$scope module tb $end
$var wire 16 ! product [15:0] $end
$var wire 1 " done $end
$var reg 1 # clk $end
$var reg 16 $ expected [15:0] $end
$var reg 8 % ip_A [7:0] $end
$var reg 8 & ip_B [7:0] $end
$var reg 9 ' prev_A [8:0] $end
$var reg 1 ( rst $end
$var reg 1 ) start $end
$var integer 32 * acc_toggles [31:0] $end
$var integer 32 + fail_count [31:0] $end
$var integer 32 , pass_count [31:0] $end
$scope module dut $end
$var wire 1 # clk $end
$var wire 8 - ip_A [7:0] $end
$var wire 8 . ip_B [7:0] $end
$var wire 1 ( rst $end
$var wire 1 ) start $end
$var reg 9 / A [8:0] $end
$var reg 1 0 C $end
$var reg 9 1 M [8:0] $end
$var reg 8 2 Q [7:0] $end
$var reg 1 3 add_en $end
$var reg 1 4 count_en $end
$var reg 4 5 counter [3:0] $end
$var reg 1 " done $end
$var reg 1 6 load_en $end
$var reg 3 7 next_state [2:0] $end
$var reg 16 8 product [15:0] $end
$var reg 1 9 shift_en $end
$var reg 1 : sign $end
$var reg 3 ; state [2:0] $end
$upscope $end
$scope task run_test $end
$var reg 8 < a [7:0] $end
$var reg 8 = b [7:0] $end
$upscope $end
$upscope $end
$enddefinitions $end
#0
$dumpvars
bx =
bx <
bx ;
x:
x9
bx 8
b0 7
x6
bx 5
x4
x3
bx 2
bx 1
x0
bx /
b0 .
b0 -
b0 ,
b0 +
b0 *
0)
1(
b0 '
b0 &
b0 %
bx $
0#
x"
bx !
$end
#5000
0"
04
09
03
06
b0 !
b0 8
b0 5
0:
00
b0 2
b0 1
b0 /
b0 ;
1#
#10000
0#
#15000
b110010 $
b101 =
b1010 <
0(
1#
#20000
0#
#25000
b1 7
1)
b101 &
b101 .
b1010 %
b1010 -
1#
#30000
0#
#35000
b10 7
16
0)
b1 ;
1#
#40000
0#
#45000
b11 7
06
b101 2
b1010 1
b10 ;
1#
#50000
0#
#55000
b100 7
13
b11 ;
1#
#60000
0#
#65000
b101 7
19
03
b1010 /
b100 ;
1#
#70000
0#
#75000
14
09
b10 7
b101 ;
b101 /
b10 2
1#
#80000
0#
#85000
b100 7
04
b1 5
b10 ;
1#
#90000
0#
#95000
b101 7
19
b100 ;
1#
#100000
0#
#105000
b10 7
14
09
b10 /
b10000001 2
b101 ;
1#
#110000
0#
#115000
04
b11 7
b10 ;
b10 5
1#
#120000
0#
#125000
b100 7
13
b11 ;
1#
#130000
0#
#135000
b101 7
19
03
b100 ;
b1100 /
1#
#140000
0#
#145000
b10 7
14
09
b110 /
b1000000 2
b101 ;
1#
#150000
0#
#155000
04
b100 7
b10 ;
b11 5
1#
#160000
0#
#165000
b101 7
19
b100 ;
1#
#170000
0#
#175000
14
09
b10 7
b101 ;
b11 /
b100000 2
1#
#180000
0#
#185000
b100 7
04
b100 5
b10 ;
1#
#190000
0#
#195000
b101 7
19
b100 ;
1#
#200000
0#
#205000
b10 7
14
09
b1 /
b10010000 2
b101 ;
1#
#210000
0#
#215000
04
b100 7
b10 ;
b101 5
1#
#220000
0#
#225000
b101 7
19
b100 ;
1#
#230000
0#
#235000
14
09
b10 7
b101 ;
b0 /
b11001000 2
1#
#240000
0#
#245000
b100 7
04
b110 5
b10 ;
1#
#250000
0#
#255000
b101 7
19
b100 ;
1#
#260000
0#
#265000
b10 7
14
09
b1100100 2
b101 ;
1#
#270000
0#
#275000
04
b100 7
b10 ;
b111 5
1#
#280000
0#
#285000
b101 7
19
b100 ;
1#
#290000
0#
#295000
14
09
b110 7
b101 ;
b110010 2
1#
#300000
0#
#305000
b0 7
1"
04
b1000 5
b110010 !
b110010 8
b110 ;
1#
#310000
0#
#315000
0"
b0 ;
b10101 $
b11 =
b111 <
b1 ,
1#
#320000
0#
#325000
b1 7
1)
b11 &
b11 .
b111 %
b111 -
1#
#330000
0#
#335000
b10 7
16
0)
b1 ;
1#
#340000
0#
#345000
b11 7
06
b0 !
b0 8
b0 5
b11 2
b111 1
b10 ;
1#
#350000
0#
#355000
b100 7
13
b11 ;
1#
#360000
0#
#365000
b101 7
19
03
b111 /
b100 ;
1#
#370000
0#
#375000
14
09
b10 7
b101 ;
b11 /
b10000001 2
1#
#380000
0#
#385000
b11 7
04
b1 5
b10 ;
1#
#390000
0#
#395000
b100 7
13
b11 ;
1#
#400000
0#
#405000
b101 7
19
03
b1010 /
b100 ;
1#
#410000
0#
#415000
14
09
b10 7
b101 ;
b101 /
b1000000 2
1#
#420000
0#
#425000
b100 7
04
b10 5
b10 ;
1#
#430000
0#
#435000
b101 7
19
b100 ;
1#
#440000
0#
#445000
b10 7
14
09
b10 /
b10100000 2
b101 ;
1#
#450000
0#
#455000
04
b100 7
b10 ;
b11 5
1#
#460000
0#
#465000
b101 7
19
b100 ;
1#
#470000
0#
#475000
14
09
b10 7
b101 ;
b1 /
b1010000 2
1#
#480000
0#
#485000
b100 7
04
b100 5
b10 ;
1#
#490000
0#
#495000
b101 7
19
b100 ;
1#
#500000
0#
#505000
b10 7
14
09
b0 /
b10101000 2
b101 ;
1#
#510000
0#
#515000
04
b100 7
b10 ;
b101 5
1#
#520000
0#
#525000
b101 7
19
b100 ;
1#
#530000
0#
#535000
14
09
b10 7
b101 ;
b1010100 2
1#
#540000
0#
#545000
b100 7
04
b110 5
b10 ;
1#
#550000
0#
#555000
b101 7
19
b100 ;
1#
#560000
0#
#565000
b10 7
14
09
b101010 2
b101 ;
1#
#570000
0#
#575000
04
b100 7
b10 ;
b111 5
1#
#580000
0#
#585000
b101 7
19
b100 ;
1#
#590000
0#
#595000
14
09
b110 7
b101 ;
b10101 2
1#
#600000
0#
#605000
b0 7
1"
04
b1000 5
b10101 !
b10101 8
b110 ;
1#
#610000
0#
#615000
0"
b0 ;
b1100100 $
b100 =
b11001 <
b10 ,
1#
#620000
0#
#625000
b1 7
1)
b100 &
b100 .
b11001 %
b11001 -
1#
#630000
0#
#635000
b10 7
16
0)
b1 ;
1#
#640000
0#
#645000
b100 7
06
b0 !
b0 8
b0 5
b100 2
b11001 1
b10 ;
1#
#650000
0#
#655000
b101 7
19
b100 ;
1#
#660000
0#
#665000
b10 7
14
09
b10 2
b101 ;
1#
#670000
0#
#675000
04
b100 7
b10 ;
b1 5
1#
#680000
0#
#685000
b101 7
19
b100 ;
1#
#690000
0#
#695000
14
09
b10 7
b101 ;
b1 2
1#
#700000
0#
#705000
b11 7
04
b10 5
b10 ;
1#
#710000
0#
#715000
b100 7
13
b11 ;
1#
#720000
0#
#725000
b101 7
19
03
b11001 /
b100 ;
1#
#730000
0#
#735000
14
09
b10 7
b101 ;
b1100 /
b10000000 2
1#
#740000
0#
#745000
b100 7
04
b11 5
b10 ;
1#
#750000
0#
#755000
b101 7
19
b100 ;
1#
#760000
0#
#765000
b10 7
14
09
b110 /
b1000000 2
b101 ;
1#
#770000
0#
#775000
04
b100 7
b10 ;
b100 5
1#
#780000
0#
#785000
b101 7
19
b100 ;
1#
#790000
0#
#795000
14
09
b10 7
b101 ;
b11 /
b100000 2
1#
#800000
0#
#805000
b100 7
04
b101 5
b10 ;
1#
#810000
0#
#815000
b101 7
19
b100 ;
1#
#820000
0#
#825000
b10 7
14
09
b1 /
b10010000 2
b101 ;
1#
#830000
0#
#835000
04
b100 7
b10 ;
b110 5
1#
#840000
0#
#845000
b101 7
19
b100 ;
1#
#850000
0#
#855000
14
09
b10 7
b101 ;
b0 /
b11001000 2
1#
#860000
0#
#865000
b100 7
04
b111 5
b10 ;
1#
#870000
0#
#875000
b101 7
19
b100 ;
1#
#880000
0#
#885000
b110 7
14
09
b1100100 2
b101 ;
1#
#890000
0#
#895000
1"
04
b0 7
b110 ;
b1000 5
b1100100 !
b1100100 8
1#
#900000
0#
#905000
0"
b0 ;
b0 $
b11001 =
b0 <
b11 ,
1#
#910000
0#
#915000
b1 7
1)
b11001 &
b11001 .
b0 %
b0 -
1#
#920000
0#
#925000
b10 7
16
0)
b1 ;
1#
#930000
0#
#935000
06
b11 7
b10 ;
b0 !
b0 8
b0 5
b11001 2
b0 1
1#
#940000
0#
#945000
b100 7
13
b11 ;
1#
#950000
0#
#955000
b101 7
19
03
b100 ;
1#
#960000
0#
#965000
b10 7
14
09
b1100 2
b101 ;
1#
#970000
0#
#975000
04
b100 7
b10 ;
b1 5
1#
#980000
0#
#985000
b101 7
19
b100 ;
1#
#990000
0#
#995000
14
09
b10 7
b101 ;
b110 2
1#
#1000000
0#
#1005000
b100 7
04
b10 5
b10 ;
1#
#1010000
0#
#1015000
b101 7
19
b100 ;
1#
#1020000
0#
#1025000
b10 7
14
09
b11 2
b101 ;
1#
#1030000
0#
#1035000
04
b11 7
b10 ;
b11 5
1#
#1040000
0#
#1045000
b100 7
13
b11 ;
1#
#1050000
0#
#1055000
b101 7
19
03
b100 ;
1#
#1060000
0#
#1065000
b10 7
14
09
b1 2
b101 ;
1#
#1070000
0#
#1075000
04
b11 7
b10 ;
b100 5
1#
#1080000
0#
#1085000
b100 7
13
b11 ;
1#
#1090000
0#
#1095000
b101 7
19
03
b100 ;
1#
#1100000
0#
#1105000
b10 7
14
09
b0 2
b101 ;
1#
#1110000
0#
#1115000
04
b100 7
b10 ;
b101 5
1#
#1120000
0#
#1125000
b101 7
19
b100 ;
1#
#1130000
0#
#1135000
b10 7
14
09
b101 ;
1#
#1140000
0#
#1145000
b100 7
04
b110 5
b10 ;
1#
#1150000
0#
#1155000
b101 7
19
b100 ;
1#
#1160000
0#
#1165000
b10 7
14
09
b101 ;
1#
#1170000
0#
#1175000
04
b100 7
b10 ;
b111 5
1#
#1180000
0#
#1185000
b101 7
19
b100 ;
1#
#1190000
0#
#1195000
b110 7
14
09
b101 ;
1#
#1200000
0#
#1205000
b0 7
1"
04
b1000 5
b110 ;
1#
#1210000
0#
#1215000
0"
b0 ;
b0 =
b11001 <
b100 ,
1#
#1220000
0#
#1225000
b1 7
1)
b0 &
b0 .
b11001 %
b11001 -
1#
#1230000
0#
#1235000
b10 7
16
0)
b1 ;
1#
#1240000
0#
#1245000
b100 7
06
b0 5
b11001 1
b10 ;
1#
#1250000
0#
#1255000
b101 7
19
b100 ;
1#
#1260000
0#
#1265000
b10 7
14
09
b101 ;
1#
#1270000
0#
#1275000
04
b100 7
b10 ;
b1 5
1#
#1280000
0#
#1285000
b101 7
19
b100 ;
1#
#1290000
0#
#1295000
b10 7
14
09
b101 ;
1#
#1300000
0#
#1305000
b100 7
04
b10 5
b10 ;
1#
#1310000
0#
#1315000
b101 7
19
b100 ;
1#
#1320000
0#
#1325000
b10 7
14
09
b101 ;
1#
#1330000
0#
#1335000
04
b100 7
b10 ;
b11 5
1#
#1340000
0#
#1345000
b101 7
19
b100 ;
1#
#1350000
0#
#1355000
b10 7
14
09
b101 ;
1#
#1360000
0#
#1365000
b100 7
04
b100 5
b10 ;
1#
#1370000
0#
#1375000
b101 7
19
b100 ;
1#
#1380000
0#
#1385000
b10 7
14
09
b101 ;
1#
#1390000
0#
#1395000
04
b100 7
b10 ;
b101 5
1#
#1400000
0#
#1405000
b101 7
19
b100 ;
1#
#1410000
0#
#1415000
b10 7
14
09
b101 ;
1#
#1420000
0#
#1425000
b100 7
04
b110 5
b10 ;
1#
#1430000
0#
#1435000
b101 7
19
b100 ;
1#
#1440000
0#
#1445000
b10 7
14
09
b101 ;
1#
#1450000
0#
#1455000
04
b100 7
b10 ;
b111 5
1#
#1460000
0#
#1465000
b101 7
19
b100 ;
1#
#1470000
0#
#1475000
b110 7
14
09
b101 ;
1#
#1480000
0#
#1485000
b0 7
1"
04
b1000 5
b110 ;
1#
#1490000
0#
#1495000
0"
b0 ;
b0 <
b101 ,
1#
#1500000
0#
#1505000
b1 7
1)
b0 %
b0 -
1#
#1510000
0#
#1515000
b10 7
16
0)
b1 ;
1#
#1520000
0#
#1525000
b100 7
06
b0 5
b0 1
b10 ;
1#
#1530000
0#
#1535000
b101 7
19
b100 ;
1#
#1540000
0#
#1545000
b10 7
14
09
b101 ;
1#
#1550000
0#
#1555000
04
b100 7
b10 ;
b1 5
1#
#1560000
0#
#1565000
b101 7
19
b100 ;
1#
#1570000
0#
#1575000
b10 7
14
09
b101 ;
1#
#1580000
0#
#1585000
b100 7
04
b10 5
b10 ;
1#
#1590000
0#
#1595000
b101 7
19
b100 ;
1#
#1600000
0#
#1605000
b10 7
14
09
b101 ;
1#
#1610000
0#
#1615000
04
b100 7
b10 ;
b11 5
1#
#1620000
0#
#1625000
b101 7
19
b100 ;
1#
#1630000
0#
#1635000
b10 7
14
09
b101 ;
1#
#1640000
0#
#1645000
b100 7
04
b100 5
b10 ;
1#
#1650000
0#
#1655000
b101 7
19
b100 ;
1#
#1660000
0#
#1665000
b10 7
14
09
b101 ;
1#
#1670000
0#
#1675000
04
b100 7
b10 ;
b101 5
1#
#1680000
0#
#1685000
b101 7
19
b100 ;
1#
#1690000
0#
#1695000
b10 7
14
09
b101 ;
1#
#1700000
0#
#1705000
b100 7
04
b110 5
b10 ;
1#
#1710000
0#
#1715000
b101 7
19
b100 ;
1#
#1720000
0#
#1725000
b10 7
14
09
b101 ;
1#
#1730000
0#
#1735000
04
b100 7
b10 ;
b111 5
1#
#1740000
0#
#1745000
b101 7
19
b100 ;
1#
#1750000
0#
#1755000
b110 7
14
09
b101 ;
1#
#1760000
0#
#1765000
b0 7
1"
04
b1000 5
b110 ;
1#
#1770000
0#
#1775000
0"
b0 ;
b1111111111000100 $
b11111011 =
b1100 <
b110 ,
1#
#1780000
0#
#1785000
b1 7
1)
b11111011 &
b11111011 .
b1100 %
b1100 -
1#
#1790000
0#
#1795000
b10 7
16
0)
b1 ;
1#
#1800000
0#
#1805000
b11 7
06
b0 5
b101 2
b1100 1
1:
b10 ;
1#
#1810000
0#
#1815000
b100 7
13
b11 ;
1#
#1820000
0#
#1825000
b101 7
19
03
b1100 /
b100 ;
1#
#1830000
0#
#1835000
14
09
b10 7
b101 ;
b110 /
b10 2
1#
#1840000
0#
#1845000
b100 7
04
b1 5
b10 ;
1#
#1850000
0#
#1855000
b101 7
19
b100 ;
1#
#1860000
0#
#1865000
b10 7
14
09
b11 /
b1 2
b101 ;
1#
#1870000
0#
#1875000
04
b11 7
b10 ;
b10 5
1#
#1880000
0#
#1885000
b100 7
13
b11 ;
1#
#1890000
0#
#1895000
b101 7
19
03
b100 ;
b1111 /
1#
#1900000
0#
#1905000
b10 7
14
09
b111 /
b10000000 2
b101 ;
1#
#1910000
0#
#1915000
04
b100 7
b10 ;
b11 5
1#
#1920000
0#
#1925000
b101 7
19
b100 ;
1#
#1930000
0#
#1935000
14
09
b10 7
b101 ;
b11 /
b11000000 2
1#
#1940000
0#
#1945000
b100 7
04
b100 5
b10 ;
1#
#1950000
0#
#1955000
b101 7
19
b100 ;
1#
#1960000
0#
#1965000
b10 7
14
09
b1 /
b11100000 2
b101 ;
1#
#1970000
0#
#1975000
04
b100 7
b10 ;
b101 5
1#
#1980000
0#
#1985000
b101 7
19
b100 ;
1#
#1990000
0#
#1995000
14
09
b10 7
b101 ;
b0 /
b11110000 2
1#
#2000000
0#
#2005000
b100 7
04
b110 5
b10 ;
1#
#2010000
0#
#2015000
b101 7
19
b100 ;
1#
#2020000
0#
#2025000
b10 7
14
09
b1111000 2
b101 ;
1#
#2030000
0#
#2035000
04
b100 7
b10 ;
b111 5
1#
#2040000
0#
#2045000
b101 7
19
b100 ;
1#
#2050000
0#
#2055000
14
09
b110 7
b101 ;
b111100 2
1#
#2060000
0#
#2065000
b0 7
1"
04
b1000 5
b1111111111000100 !
b1111111111000100 8
b110 ;
1#
#2070000
0#
#2075000
0"
b0 ;
b1111111111001000 $
b111 =
b11111000 <
b111 ,
1#
#2080000
0#
#2085000
b1 7
1)
b111 &
b111 .
b11111000 %
b11111000 -
1#
#2090000
0#
#2095000
b10 7
16
0)
b1 ;
1#
#2100000
0#
#2105000
b11 7
06
b0 !
b0 8
b0 5
b111 2
b1000 1
b10 ;
1#
#2110000
0#
#2115000
b100 7
13
b11 ;
1#
#2120000
0#
#2125000
b101 7
19
03
b1000 /
b100 ;
1#
#2130000
0#
#2135000
14
09
b10 7
b101 ;
b100 /
b11 2
1#
#2140000
0#
#2145000
b11 7
04
b1 5
b10 ;
1#
#2150000
0#
#2155000
b100 7
13
b11 ;
1#
#2160000
0#
#2165000
b101 7
19
03
b1100 /
b100 ;
1#
#2170000
0#
#2175000
14
09
b10 7
b101 ;
b110 /
b1 2
1#
#2180000
0#
#2185000
b11 7
04
b10 5
b10 ;
1#
#2190000
0#
#2195000
b100 7
13
b11 ;
1#
#2200000
0#
#2205000
b101 7
19
03
b1110 /
b100 ;
1#
#2210000
0#
#2215000
14
09
b10 7
b101 ;
b111 /
b0 2
1#
#2220000
0#
#2225000
b100 7
04
b11 5
b10 ;
1#
#2230000
0#
#2235000
b101 7
19
b100 ;
1#
#2240000
0#
#2245000
b10 7
14
09
b11 /
b10000000 2
b101 ;
1#
#2250000
0#
#2255000
04
b100 7
b10 ;
b100 5
1#
#2260000
0#
#2265000
b101 7
19
b100 ;
1#
#2270000
0#
#2275000
14
09
b10 7
b101 ;
b1 /
b11000000 2
1#
#2280000
0#
#2285000
b100 7
04
b101 5
b10 ;
1#
#2290000
0#
#2295000
b101 7
19
b100 ;
1#
#2300000
0#
#2305000
b10 7
14
09
b0 /
b11100000 2
b101 ;
1#
#2310000
0#
#2315000
04
b100 7
b10 ;
b110 5
1#
#2320000
0#
#2325000
b101 7
19
b100 ;
1#
#2330000
0#
#2335000
14
09
b10 7
b101 ;
b1110000 2
1#
#2340000
0#
#2345000
b100 7
04
b111 5
b10 ;
1#
#2350000
0#
#2355000
b101 7
19
b100 ;
1#
#2360000
0#
#2365000
b110 7
14
09
b111000 2
b101 ;
1#
#2370000
0#
#2375000
1"
04
b0 7
b110 ;
b1000 5
b1111111111001000 !
b1111111111001000 8
1#
#2380000
0#
#2385000
0"
b0 ;
b1011010 $
b11110111 =
b11110110 <
b1000 ,
1#
#2390000
0#
#2395000
b1 7
1)
b11110111 &
b11110111 .
b11110110 %
b11110110 -
1#
#2400000
0#
#2405000
b10 7
16
0)
b1 ;
1#
#2410000
0#
#2415000
06
b11 7
b10 ;
b0 !
b0 8
b0 5
b1001 2
b1010 1
0:
1#
#2420000
0#
#2425000
b100 7
13
b11 ;
1#
#2430000
0#
#2435000
b101 7
19
03
b100 ;
b1010 /
1#
#2440000
0#
#2445000
b10 7
14
09
b101 /
b100 2
b101 ;
1#
#2450000
0#
#2455000
04
b100 7
b10 ;
b1 5
1#
#2460000
0#
#2465000
b101 7
19
b100 ;
1#
#2470000
0#
#2475000
14
09
b10 7
b101 ;
b10 /
b10000010 2
1#
#2480000
0#
#2485000
b100 7
04
b10 5
b10 ;
1#
#2490000
0#
#2495000
b101 7
19
b100 ;
1#
#2500000
0#
#2505000
b10 7
14
09
b1 /
b1000001 2
b101 ;
1#
#2510000
0#
#2515000
04
b11 7
b10 ;
b11 5
1#
#2520000
0#
#2525000
b100 7
13
b11 ;
1#
#2530000
0#
#2535000
b101 7
19
03
b100 ;
b1011 /
1#
#2540000
0#
#2545000
b10 7
14
09
b101 /
b10100000 2
b101 ;
1#
#2550000
0#
#2555000
04
b100 7
b10 ;
b100 5
1#
#2560000
0#
#2565000
b101 7
19
b100 ;
1#
#2570000
0#
#2575000
14
09
b10 7
b101 ;
b10 /
b11010000 2
1#
#2580000
0#
#2585000
b100 7
04
b101 5
b10 ;
1#
#2590000
0#
#2595000
b101 7
19
b100 ;
1#
#2600000
0#
#2605000
b10 7
14
09
b1 /
b1101000 2
b101 ;
1#
#2610000
0#
#2615000
04
b100 7
b10 ;
b110 5
1#
#2620000
0#
#2625000
b101 7
19
b100 ;
1#
#2630000
0#
#2635000
14
09
b10 7
b101 ;
b0 /
b10110100 2
1#
#2640000
0#
#2645000
b100 7
04
b111 5
b10 ;
1#
#2650000
0#
#2655000
b101 7
19
b100 ;
1#
#2660000
0#
#2665000
b110 7
14
09
b1011010 2
b101 ;
1#
#2670000
0#
#2675000
1"
04
b0 7
b110 ;
b1000 5
b1011010 !
b1011010 8
1#
#2680000
0#
#2685000
0"
b0 ;
b101 $
b11111111 =
b11111011 <
b1001 ,
1#
#2690000
0#
#2695000
b1 7
1)
b11111111 &
b11111111 .
b11111011 %
b11111011 -
1#
#2700000
0#
#2705000
b10 7
16
0)
b1 ;
1#
#2710000
0#
#2715000
06
b11 7
b10 ;
b0 !
b0 8
b0 5
b1 2
b101 1
1#
#2720000
0#
#2725000
b100 7
13
b11 ;
1#
#2730000
0#
#2735000
b101 7
19
03
b100 ;
b101 /
1#
#2740000
0#
#2745000
b10 7
14
09
b10 /
b10000000 2
b101 ;
1#
#2750000
0#
#2755000
04
b100 7
b10 ;
b1 5
1#
#2760000
0#
#2765000
b101 7
19
b100 ;
1#
#2770000
0#
#2775000
14
09
b10 7
b101 ;
b1 /
b1000000 2
1#
#2780000
0#
#2785000
b100 7
04
b10 5
b10 ;
1#
#2790000
0#
#2795000
b101 7
19
b100 ;
1#
#2800000
0#
#2805000
b10 7
14
09
b0 /
b10100000 2
b101 ;
1#
#2810000
0#
#2815000
04
b100 7
b10 ;
b11 5
1#
#2820000
0#
#2825000
b101 7
19
b100 ;
1#
#2830000
0#
#2835000
14
09
b10 7
b101 ;
b1010000 2
1#
#2840000
0#
#2845000
b100 7
04
b100 5
b10 ;
1#
#2850000
0#
#2855000
b101 7
19
b100 ;
1#
#2860000
0#
#2865000
b10 7
14
09
b101000 2
b101 ;
1#
#2870000
0#
#2875000
04
b100 7
b10 ;
b101 5
1#
#2880000
0#
#2885000
b101 7
19
b100 ;
1#
#2890000
0#
#2895000
14
09
b10 7
b101 ;
b10100 2
1#
#2900000
0#
#2905000
b100 7
04
b110 5
b10 ;
1#
#2910000
0#
#2915000
b101 7
19
b100 ;
1#
#2920000
0#
#2925000
b10 7
14
09
b1010 2
b101 ;
1#
#2930000
0#
#2935000
04
b100 7
b10 ;
b111 5
1#
#2940000
0#
#2945000
b101 7
19
b100 ;
1#
#2950000
0#
#2955000
14
09
b110 7
b101 ;
b101 2
1#
#2960000
0#
#2965000
b0 7
1"
04
b1000 5
b101 !
b101 8
b110 ;
1#
#2970000
0#
#2975000
0"
b0 ;
b1111111 $
b1 =
b1111111 <
b1010 ,
1#
#2980000
0#
#2985000
b1 7
1)
b1 &
b1 .
b1111111 %
b1111111 -
1#
#2990000
0#
#2995000
b10 7
16
0)
b1 ;
1#
#3000000
0#
#3005000
b11 7
06
b0 !
b0 8
b0 5
b1 2
b1111111 1
b10 ;
1#
#3010000
0#
#3015000
b100 7
13
b11 ;
1#
#3020000
0#
#3025000
b101 7
19
03
b1111111 /
b100 ;
1#
#3030000
0#
#3035000
14
09
b10 7
b101 ;
b111111 /
b10000000 2
1#
#3040000
0#
#3045000
b100 7
04
b1 5
b10 ;
1#
#3050000
0#
#3055000
b101 7
19
b100 ;
1#
#3060000
0#
#3065000
b10 7
14
09
b11111 /
b11000000 2
b101 ;
1#
#3070000
0#
#3075000
04
b100 7
b10 ;
b10 5
1#
#3080000
0#
#3085000
b101 7
19
b100 ;
1#
#3090000
0#
#3095000
14
09
b10 7
b101 ;
b1111 /
b11100000 2
1#
#3100000
0#
#3105000
b100 7
04
b11 5
b10 ;
1#
#3110000
0#
#3115000
b101 7
19
b100 ;
1#
#3120000
0#
#3125000
b10 7
14
09
b111 /
b11110000 2
b101 ;
1#
#3130000
0#
#3135000
04
b100 7
b10 ;
b100 5
1#
#3140000
0#
#3145000
b101 7
19
b100 ;
1#
#3150000
0#
#3155000
14
09
b10 7
b101 ;
b11 /
b11111000 2
1#
#3160000
0#
#3165000
b100 7
04
b101 5
b10 ;
1#
#3170000
0#
#3175000
b101 7
19
b100 ;
1#
#3180000
0#
#3185000
b10 7
14
09
b1 /
b11111100 2
b101 ;
1#
#3190000
0#
#3195000
04
b100 7
b10 ;
b110 5
1#
#3200000
0#
