booth_multiplier_seq.v
module booth_multiplier_seq #(
    parameter WIDTH = 8
)(
    input  wire                     clk,
    input  wire                     rst,
    input  wire                     start,
    input  wire signed [WIDTH-1:0]         ip_A,
    input  wire signed [WIDTH-1:0]         ip_B,

    output reg  signed [2*WIDTH-1:0]       product,
    output reg                      done
);


// State Encoding

localparam IDLE  = 3'd0,
           LOAD  = 3'd1,
           CHECK = 3'd2,
           ADD   = 3'd3,
           SUB   = 3'd4,
           SHIFT = 3'd5,
           COUNT = 3'd6,
           DONE  = 3'd7;

reg [2:0] state, next_state;

// Datapath Registers

reg signed [WIDTH:0] A;
reg signed [WIDTH:0] M;
reg        [WIDTH-1:0] Q;
reg Q_1;

localparam COUNT_W = $clog2(WIDTH);
reg [COUNT_W:0] counter;

// Control Signals

reg load_en;
reg add_en;
reg sub_en;
reg shift_en;
reg count_en;

// Output Logic

always @(*) begin

    load_en  = 1'b0;
    add_en   = 1'b0;
    sub_en   = 1'b0;
    shift_en = 1'b0;
    count_en = 1'b0;
    done     = 1'b0;

    case (state)

        LOAD  : load_en  = 1'b1;
        ADD   : add_en   = 1'b1;
        SUB   : sub_en   = 1'b1;
        SHIFT : shift_en = 1'b1;
        COUNT : count_en = 1'b1;
        DONE  : done     = 1'b1;

        default: ;

    endcase

end

// Next-State Logic

always @(*) begin

    next_state = state;

    case (state)

        IDLE:
            if (start)
                next_state = LOAD;

        LOAD:
            next_state = CHECK;

        CHECK:
            case ({Q[0], Q_1})

                2'b00,
                2'b11: next_state = SHIFT;

                2'b01: next_state = ADD;

                2'b10: next_state = SUB;

                default: next_state = SHIFT;

            endcase

        ADD:
            next_state = SHIFT;

        SUB:
            next_state = SHIFT;

        SHIFT:
            next_state = COUNT;

        COUNT:
            if (counter == WIDTH-1)
                next_state = DONE;
            else
                next_state = CHECK;

        DONE:
            next_state = IDLE;

        default:
            next_state = IDLE;

    endcase

end


// Datapath

always @(posedge clk) begin

    if (rst) begin

        A       <= '0;
        M       <= '0;
        Q       <= '0;
        Q_1     <= 1'b0;
        counter <= '0;
        product <= '0;

    end
    else begin

        if (load_en) begin

            A       <= '0;
            M       <= {ip_A[WIDTH-1], ip_A};
            Q       <= ip_B;
            Q_1     <= 1'b0;
            counter <= '0;
            product <= '0;

        end
        else if (add_en) begin

            A <= A + M;

        end
        else if (sub_en) begin

            A <= A - M;

        end
        else if (shift_en) begin

            Q_1 <= Q[0];
            Q   <= {A[0], Q[WIDTH-1:1]};
            A   <= {A[WIDTH], A[WIDTH:1]};

        end
        else if (count_en) begin

            if (counter == WIDTH-1)
                product <= {A[WIDTH-1:0], Q};

            counter <= counter + 1'b1;

        end

    end

end

// State Register

always @(posedge clk) begin

    if (rst)
        state <= IDLE;
    else
        state <= next_state;

end

endmodule

tb_booth.v
`timescale 1ns/1ps

module tb_seq;

parameter WIDTH = 8;

reg clk;
reg rst;
reg start;

reg signed [WIDTH-1:0] ip_A;
reg signed [WIDTH-1:0] ip_B;

wire signed [2*WIDTH-1:0] product;
wire done;

//--------------------------------------------------
// DUT
//--------------------------------------------------

booth_multiplier_seq #(
    .WIDTH(WIDTH)
) dut (
    .clk(clk),
    .rst(rst),
    .start(start),
    .ip_A(ip_A),
    .ip_B(ip_B),
    .product(product),
    .done(done)
);

//--------------------------------------------------
// Clock
//--------------------------------------------------

initial begin
    clk = 0;
    forever #5 clk = ~clk;
end

//--------------------------------------------------
// Statistics
//--------------------------------------------------

integer pass_count = 0;
integer fail_count = 0;

integer add_ops = 0;
integer sub_ops = 0;
integer total_mults = 0;

reg signed [2*WIDTH-1:0] expected;

//--------------------------------------------------
// Count arithmetic operations
//--------------------------------------------------

always @(posedge clk) begin
    if(!rst) begin

        if(dut.add_en)
            add_ops <= add_ops + 1;

        if(dut.sub_en)
            sub_ops <= sub_ops + 1;

        if(done)
            total_mults <= total_mults + 1;

    end
end

//--------------------------------------------------
// Test Task
//--------------------------------------------------

task run_test;

    input signed [WIDTH-1:0] a;
    input signed [WIDTH-1:0] b;

    begin

        expected = a * b;

        @(posedge clk);
        ip_A  <= a;
        ip_B  <= b;
        start <= 1'b1;

        @(posedge clk);
        start <= 1'b0;

        wait(done);
        @(posedge clk);

        if(product === expected)
            pass_count = pass_count + 1;
        else begin
            fail_count = fail_count + 1;

            $display("----------------------------------------");
            $display("FAILED");
            $display("A        = %0d", a);
            $display("B        = %0d", b);
            $display("Expected = %0d", expected);
            $display("Obtained = %0d", product);
        end

    end

endtask

//--------------------------------------------------
// Test Sequence
//--------------------------------------------------

initial begin

    rst   = 1;
    start = 0;
    ip_A  = 0;
    ip_B  = 0;

    repeat(2) @(posedge clk);
    rst = 0;

    //==================================================
    // Directed Benchmark
    //==================================================

    // Dataset 1 : Multiplicand = 0x55
    run_test(8'h55, 8'b11111111);
    run_test(8'h55, 8'b11111110);
    run_test(8'h55, 8'b11111100);
    run_test(8'h55, 8'b11111000);
    run_test(8'h55, 8'b11110000);
    run_test(8'h55, 8'b01111111);
    run_test(8'h55, 8'b00111111);
    run_test(8'h55, 8'b00011111);
    run_test(8'h55, 8'b00001111);
    run_test(8'h55, 8'b00000111);

    // Dataset 2 : Multiplicand = 0xD3
    run_test(8'hD3, 8'b11111111);
    run_test(8'hD3, 8'b11111110);
    run_test(8'hD3, 8'b11111100);
    run_test(8'hD3, 8'b11111000);
    run_test(8'hD3, 8'b11110000);
    run_test(8'hD3, 8'b01111111);
    run_test(8'hD3, 8'b00111111);
    run_test(8'hD3, 8'b00011111);
    run_test(8'hD3, 8'b00001111);
    run_test(8'hD3, 8'b00000111);

    @(posedge clk);

    //==================================================
    // Summary
    //==================================================

    $display("\n==========================================");
    $display("Directed Benchmark Summary");
    $display("------------------------------------------");
    $display("Tests Passed              : %0d", pass_count);
    $display("Tests Failed              : %0d", fail_count);
    $display("Total ADD Operations      : %0d", add_ops);
    $display("Total SUB Operations      : %0d", sub_ops);
    $display("Total Arithmetic Ops      : %0d", add_ops + sub_ops);
    $display("Total Multiplications     : %0d", total_mults);

    if(total_mults != 0) begin
        $display("Average ADDs/Multiply     : %.2f",
                add_ops*1.0/total_mults);

        $display("Average SUBs/Multiply     : %.2f",
                sub_ops*1.0/total_mults);

        $display("Average Ops/Multiply      : %.2f",
                (add_ops+sub_ops)*1.0/total_mults);
    end

    $display("==========================================");

    #20;
    $finish;

end

//--------------------------------------------------
// Waveforms
//--------------------------------------------------

initial begin
    $dumpfile("seq_multiplier.vcd");
    $dumpvars(0, tb_seq);
end

endmodule

seq_multiplier.vcd
$date
	Tue Jun 30 08:16:43 2026
$end
$version
	Icarus Verilog
$end
$timescale
	1ps
$end
$scope module tb_seq $end
$var wire 16 ! product [15:0] $end
$var wire 1 " done $end
$var reg 1 # clk $end
$var reg 16 $ expected [15:0] $end
$var reg 8 % ip_A [7:0] $end
$var reg 8 & ip_B [7:0] $end
$var reg 1 ' rst $end
$var reg 1 ( start $end
$var integer 32 ) add_ops [31:0] $end
$var integer 32 * fail_count [31:0] $end
$var integer 32 + pass_count [31:0] $end
$var integer 32 , sub_ops [31:0] $end
$var integer 32 - total_mults [31:0] $end
$scope module dut $end
$var wire 1 # clk $end
$var wire 8 . ip_A [7:0] $end
$var wire 8 / ip_B [7:0] $end
$var wire 1 ' rst $end
$var wire 1 ( start $end
$var reg 9 0 A [8:0] $end
$var reg 9 1 M [8:0] $end
$var reg 8 2 Q [7:0] $end
$var reg 1 3 Q_1 $end
$var reg 1 4 add_en $end
$var reg 1 5 count_en $end
$var reg 4 6 counter [3:0] $end
$var reg 1 " done $end
$var reg 1 7 load_en $end
$var reg 3 8 next_state [2:0] $end
$var reg 16 9 product [15:0] $end
$var reg 1 : shift_en $end
$var reg 3 ; state [2:0] $end
$var reg 1 < sub_en $end
$upscope $end
$scope task run_test $end
$var reg 8 = a [7:0] $end
$var reg 8 > b [7:0] $end
$upscope $end
$upscope $end
$enddefinitions $end
#0
$dumpvars
bx >
bx =
x<
bx ;
x:
bx 9
b0 8
x7
bx 6
x5
x4
x3
bx 2
bx 1
bx 0
b0 /
b0 .
b0 -
b0 ,
b0 +
b0 *
b0 )
0(
1'
b0 &
b0 %
bx $
0#
x"
bx !
$end
#5000
0"
05
0:
0<
04
07
b0 !
b0 9
b0 6
03
b0 2
b0 1
b0 0
b0 ;
1#
#10000
0#
#15000
b1111111110101011 $
b11111111 >
b1010101 =
0'
1#
#20000
0#
#25000
b1 8
1(
b11111111 &
b11111111 /
b1010101 %
b1010101 .
1#
#30000
0#
#35000
b10 8
17
0(
b1 ;
1#
#40000
0#
#45000
b100 8
07
b11111111 2
b1010101 1
b10 ;
1#
#50000
0#
#55000
b101 8
1<
b100 ;
1#
#60000
0#
#65000
b110 8
1:
0<
b110101011 0
b101 ;
b1 ,
1#
#70000
0#
#75000
15
0:
b10 8
b110 ;
b111010101 0
13
1#
#80000
0#
#85000
b101 8
05
b1 6
b10 ;
1#
#90000
0#
#95000
b110 8
1:
b101 ;
1#
#100000
0#
#105000
b10 8
15
0:
b111101010 0
b110 ;
1#
#110000
0#
#115000
05
b101 8
b10 ;
b10 6
1#
#120000
0#
#125000
b110 8
1:
b101 ;
1#
#130000
0#
#135000
15
0:
b10 8
b110 ;
b111110101 0
b1111111 2
1#
#140000
0#
#145000
b101 8
05
b11 6
b10 ;
1#
#150000
0#
#155000
b110 8
1:
b101 ;
1#
#160000
0#
#165000
b10 8
15
0:
b111111010 0
b10111111 2
b110 ;
1#
#170000
0#
#175000
05
b101 8
b10 ;
b100 6
1#
#180000
0#
#185000
b110 8
1:
b101 ;
1#
#190000
0#
#195000
15
0:
b10 8
b110 ;
b111111101 0
b1011111 2
1#
#200000
0#
#205000
b101 8
05
b101 6
b10 ;
1#
#210000
0#
#215000
b110 8
1:
b101 ;
1#
#220000
0#
#225000
b10 8
15
0:
b111111110 0
b10101111 2
b110 ;
1#
#230000
0#
#235000
05
b101 8
b10 ;
b110 6
1#
#240000
0#
#245000
b110 8
1:
b101 ;
1#
#250000
0#
#255000
15
0:
b10 8
b110 ;
b111111111 0
b1010111 2
1#
#260000
0#
#265000
b101 8
05
b111 6
b10 ;
1#
#270000
0#
#275000
b110 8
1:
b101 ;
1#
#280000
0#
#285000
b111 8
15
0:
b10101011 2
b110 ;
1#
#290000
0#
#295000
1"
05
b0 8
b111 ;
b1000 6
b1111111110101011 !
b1111111110101011 9
1#
#300000
0#
#305000
0"
b0 ;
b1 -
b1111111101010110 $
b11111110 >
b1 +
1#
#310000
0#
#315000
b1 8
1(
b11111110 &
b11111110 /
1#
#320000
0#
#325000
b10 8
17
0(
b1 ;
1#
#330000
0#
#335000
07
b101 8
b10 ;
b0 !
b0 9
b0 6
03
b11111110 2
b0 0
1#
#340000
0#
#345000
b110 8
1:
b101 ;
1#
#350000
0#
#355000
15
0:
b10 8
b110 ;
b1111111 2
1#
#360000
0#
#365000
b100 8
05
b1 6
b10 ;
1#
#370000
0#
#375000
b101 8
1<
b100 ;
1#
#380000
0#
#385000
b110 8
1:
0<
b110101011 0
b101 ;
b10 ,
1#
#390000
0#
#395000
15
0:
b10 8
b110 ;
b111010101 0
b10111111 2
13
1#
#400000
0#
#405000
b101 8
05
b10 6
b10 ;
1#
#410000
0#
#415000
b110 8
1:
b101 ;
1#
#420000
0#
#425000
b10 8
15
0:
b111101010 0
b11011111 2
b110 ;
1#
#430000
0#
#435000
05
b101 8
b10 ;
b11 6
1#
#440000
0#
#445000
b110 8
1:
b101 ;
1#
#450000
0#
#455000
15
0:
b10 8
b110 ;
b111110101 0
b1101111 2
1#
#460000
0#
#465000
b101 8
05
b100 6
b10 ;
1#
#470000
0#
#475000
b110 8
1:
b101 ;
1#
#480000
0#
#485000
b10 8
15
0:
b111111010 0
b10110111 2
b110 ;
1#
#490000
0#
#495000
05
b101 8
b10 ;
b101 6
1#
#500000
0#
#505000
b110 8
1:
b101 ;
1#
#510000
0#
#515000
15
0:
b10 8
b110 ;
b111111101 0
b1011011 2
1#
#520000
0#
#525000
b101 8
05
b110 6
b10 ;
1#
#530000
0#
#535000
b110 8
1:
b101 ;
1#
#540000
0#
#545000
b10 8
15
0:
b111111110 0
b10101101 2
b110 ;
1#
#550000
0#
#555000
05
b101 8
b10 ;
b111 6
1#
#560000
0#
#565000
b110 8
1:
b101 ;
1#
#570000
0#
#575000
15
0:
b111 8
b110 ;
b111111111 0
b1010110 2
1#
#580000
0#
#585000
b0 8
1"
05
b1000 6
b1111111101010110 !
b1111111101010110 9
b111 ;
1#
#590000
0#
#595000
0"
b10 -
b0 ;
b1111111010101100 $
b11111100 >
b10 +
1#
#600000
0#
#605000
b1 8
1(
b11111100 &
b11111100 /
1#
#610000
0#
#615000
b10 8
17
0(
b1 ;
1#
#620000
0#
#625000
b101 8
07
b0 !
b0 9
b0 6
03
b11111100 2
b0 0
b10 ;
1#
#630000
0#
#635000
b110 8
1:
b101 ;
1#
#640000
0#
#645000
b10 8
15
0:
b1111110 2
b110 ;
1#
#650000
0#
#655000
05
b101 8
b10 ;
b1 6
1#
#660000
0#
#665000
b110 8
1:
b101 ;
1#
#670000
0#
#675000
15
0:
b10 8
b110 ;
b111111 2
1#
#680000
0#
#685000
b100 8
05
b10 6
b10 ;
1#
#690000
0#
#695000
b101 8
1<
b100 ;
1#
#700000
0#
#705000
b110 8
1:
0<
b110101011 0
b101 ;
b11 ,
1#
#710000
0#
#715000
15
0:
b10 8
b110 ;
b111010101 0
b10011111 2
13
1#
#720000
0#
#725000
b101 8
05
b11 6
b10 ;
1#
#730000
0#
#735000
b110 8
1:
b101 ;
1#
#740000
0#
#745000
b10 8
15
0:
b111101010 0
b11001111 2
b110 ;
1#
#750000
0#
#755000
05
b101 8
b10 ;
b100 6
1#
#760000
0#
#765000
b110 8
1:
b101 ;
1#
#770000
0#
#775000
15
0:
b10 8
b110 ;
b111110101 0
b1100111 2
1#
#780000
0#
#785000
b101 8
05
b101 6
b10 ;
1#
#790000
0#
#795000
b110 8
1:
b101 ;
1#
#800000
0#
#805000
b10 8
15
0:
b111111010 0
b10110011 2
b110 ;
1#
#810000
0#
#815000
05
b101 8
b10 ;
b110 6
1#
#820000
0#
#825000
b110 8
1:
b101 ;
1#
#830000
0#
#835000
15
0:
b10 8
b110 ;
b111111101 0
b1011001 2
1#
#840000
0#
#845000
b101 8
05
b111 6
b10 ;
1#
#850000
0#
#855000
b110 8
1:
b101 ;
1#
#860000
0#
#865000
b111 8
15
0:
b111111110 0
b10101100 2
b110 ;
1#
#870000
0#
#875000
1"
05
b0 8
b111 ;
b1000 6
b1111111010101100 !
b1111111010101100 9
1#
#880000
0#
#885000
0"
b0 ;
b11 -
b1111110101011000 $
b11111000 >
b11 +
1#
#890000
0#
#895000
b1 8
1(
b11111000 &
b11111000 /
1#
#900000
0#
#905000
b10 8
17
0(
b1 ;
1#
#910000
0#
#915000
07
b101 8
b10 ;
b0 !
b0 9
b0 6
03
b11111000 2
b0 0
1#
#920000
0#
#925000
b110 8
1:
b101 ;
1#
#930000
0#
#935000
15
0:
b10 8
b110 ;
b1111100 2
1#
#940000
0#
#945000
b101 8
05
b1 6
b10 ;
1#
#950000
0#
#955000
b110 8
1:
b101 ;
1#
#960000
0#
#965000
b10 8
15
0:
b111110 2
b110 ;
1#
#970000
0#
#975000
05
b101 8
b10 ;
b10 6
1#
#980000
0#
#985000
b110 8
1:
b101 ;
1#
#990000
0#
#995000
15
0:
b10 8
b110 ;
b11111 2
1#
#1000000
0#
#1005000
b100 8
05
b11 6
b10 ;
1#
#1010000
0#
#1015000
b101 8
1<
b100 ;
1#
#1020000
0#
#1025000
b110 8
1:
0<
b110101011 0
b101 ;
b100 ,
1#
#1030000
0#
#1035000
15
0:
b10 8
b110 ;
b111010101 0
b10001111 2
13
1#
#1040000
0#
#1045000
b101 8
05
b100 6
b10 ;
1#
#1050000
0#
#1055000
b110 8
1:
b101 ;
1#
#1060000
0#
#1065000
b10 8
15
0:
b111101010 0
b11000111 2
b110 ;
1#
#1070000
0#
#1075000
05
b101 8
b10 ;
b101 6
1#
#1080000
0#
#1085000
b110 8
1:
b101 ;
1#
#1090000
0#
#1095000
15
0:
b10 8
b110 ;
b111110101 0
b1100011 2
1#
#1100000
0#
#1105000
b101 8
05
b110 6
b10 ;
1#
#1110000
0#
#1115000
b110 8
1:
b101 ;
1#
#1120000
0#
#1125000
b10 8
15
0:
b111111010 0
b10110001 2
b110 ;
1#
#1130000
0#
#1135000
05
b101 8
b10 ;
b111 6
1#
#1140000
0#
#1145000
b110 8
1:
b101 ;
1#
#1150000
0#
#1155000
15
0:
b111 8
b110 ;
b111111101 0
b1011000 2
1#
#1160000
0#
#1165000
b0 8
1"
05
b1000 6
b1111110101011000 !
b1111110101011000 9
b111 ;
1#
#1170000
0#
#1175000
0"
b100 -
b0 ;
b1111101010110000 $
b11110000 >
b100 +
1#
#1180000
0#
#1185000
b1 8
1(
b11110000 &
b11110000 /
1#
#1190000
0#
#1195000
b10 8
17
0(
b1 ;
1#
#1200000
0#
#1205000
b101 8
07
b0 !
b0 9
b0 6
03
b11110000 2
b0 0
b10 ;
1#
#1210000
0#
#1215000
b110 8
1:
b101 ;
1#
#1220000
0#
#1225000
b10 8
15
0:
b1111000 2
b110 ;
1#
#1230000
0#
#1235000
05
b101 8
b10 ;
b1 6
1#
#1240000
0#
#1245000
b110 8
1:
b101 ;
1#
#1250000
0#
#1255000
15
0:
b10 8
b110 ;
b111100 2
1#
#1260000
0#
#1265000
b101 8
05
b10 6
b10 ;
1#
#1270000
0#
#1275000
b110 8
1:
b101 ;
1#
#1280000
0#
#1285000
b10 8
15
0:
b11110 2
b110 ;
1#
#1290000
0#
#1295000
05
b101 8
b10 ;
b11 6
1#
#1300000
0#
#1305000
b110 8
1:
b101 ;
1#
#1310000
0#
#1315000
15
0:
b10 8
b110 ;
b1111 2
1#
#1320000
0#
#1325000
b100 8
05
b100 6
b10 ;
1#
#1330000
0#
#1335000
b101 8
1<
b100 ;
1#
#1340000
0#
#1345000
b110 8
1:
0<
b110101011 0
b101 ;
b101 ,
1#
#1350000
0#
#1355000
15
0:
b10 8
b110 ;
b111010101 0
b10000111 2
13
1#
#1360000
0#
#1365000
b101 8
05
b101 6
b10 ;
1#
#1370000
0#
#1375000
b110 8
1:
b101 ;
1#
#1380000
0#
#1385000
b10 8
15
0:
b111101010 0
b11000011 2
b110 ;
1#
#1390000
0#
#1395000
05
b101 8
b10 ;
b110 6
1#
#1400000
0#
#1405000
b110 8
1:
b101 ;
1#
#1410000
0#
#1415000
15
0:
b10 8
b110 ;
b111110101 0
b1100001 2
1#
#1420000
0#
#1425000
b101 8
05
b111 6
b10 ;
1#
#1430000
0#
#1435000
b110 8
1:
b101 ;
1#
#1440000
0#
#1445000
b111 8
15
0:
b111111010 0
b10110000 2
b110 ;
1#
#1450000
0#
#1455000
1"
05
b0 8
b111 ;
b1000 6
b1111101010110000 !
b1111101010110000 9
1#
#1460000
0#
#1465000
0"
b0 ;
b101 -
b10101000101011 $
b1111111 >
b101 +
1#
#1470000
0#
#1475000
b1 8
1(
b1111111 &
b1111111 /
1#
#1480000
0#
#1485000
b10 8
17
0(
b1 ;
1#
#1490000
0#
#1495000
07
b100 8
b10 ;
b0 !
b0 9
b0 6
03
b1111111 2
b0 0
1#
#1500000
0#
#1505000
b101 8
1<
b100 ;
1#
#1510000
0#
#1515000
b110 8
1:
0<
b110 ,
b101 ;
b110101011 0
1#
#1520000
0#
#1525000
b10 8
15
0:
b111010101 0
b10111111 2
13
b110 ;
1#
#1530000
0#
#1535000
05
b101 8
b10 ;
b1 6
1#
#1540000
0#
#1545000
b110 8
1:
b101 ;
1#
#1550000
0#
#1555000
15
0:
b10 8
b110 ;
b111101010 0
b11011111 2
1#
#1560000
0#
#1565000
b101 8
05
b10 6
b10 ;
1#
#1570000
0#
#1575000
b110 8
1:
b101 ;
1#
#1580000
0#
#1585000
b10 8
15
0:
b111110101 0
b1101111 2
b110 ;
1#
#1590000
0#
#1595000
05
b101 8
b10 ;
b11 6
1#
#1600000
0#
#1605000
b110 8
1:
b101 ;
1#
#1610000
0#
#1615000
15
0:
b10 8
b110 ;
b111111010 0
b10110111 2
1#
#1620000
0#
#1625000
b101 8
05
b100 6
b10 ;
1#
#1630000
0#
#1635000
b110 8
1:
b101 ;
1#
#1640000
0#
#1645000
b10 8
15
0:
b111111101 0
b1011011 2
b110 ;
1#
#1650000
0#
#1655000
05
b101 8
b10 ;
b101 6
1#
#1660000
0#
#1665000
b110 8
1:
b101 ;
1#
#1670000
0#
#1675000
15
0:
b10 8
b110 ;
b111111110 0
b10101101 2
1#
#1680000
0#
#1685000
b101 8
05
b110 6
b10 ;
1#
#1690000
0#
#1695000
b110 8
1:
b101 ;
1#
#1700000
0#
#1705000
b10 8
15
0:
b111111111 0
b1010110 2
b110 ;
1#
#1710000
0#
#1715000
05
b11 8
b10 ;
b111 6
1#
#1720000
0#
#1725000
b101 8
14
b11 ;
1#
#1730000
0#
#1735000
b110 8
1:
04
b1 )
b101 ;
b1010100 0
1#
#1740000
0#
#1745000
b111 8
15
0:
b101010 0
b101011 2
03
b110 ;
1#
#1750000
0#
#1755000
1"
05
b0 8
b111 ;
b1000 6
b10101000101011 !
b10101000101011 9
1#
#1760000
0#
#1765000
0"
b0 ;
b110 -
b1010011101011 $
b111111 >
b110 +
1#
#1770000
0#
#1775000
b1 8
1(
b111111 &
b111111 /
1#
#1780000
0#
#1785000
b10 8
17
0(
b1 ;
1#
#1790000
0#
#1795000
07
b100 8
b10 ;
b0 !
b0 9
b0 6
b111111 2
b0 0
1#
#1800000
0#
#1805000
b101 8
1<
b100 ;
1#
#1810000
0#
#1815000
b110 8
1:
0<
b111 ,
b101 ;
b110101011 0
1#
#1820000
0#
#1825000
b10 8
15
0:
b111010101 0
b10011111 2
13
b110 ;
1#
#1830000
0#
#1835000
05
b101 8
b10 ;
b1 6
1#
#1840000
0#
#1845000
b110 8
1:
b101 ;
1#
#1850000
0#
#1855000
15
0:
b10 8
b110 ;
b111101010 0
b11001111 2
1#
#1860000
0#
#1865000
b101 8
05
b10 6
b10 ;
1#
#1870000
0#
#1875000
b110 8
1:
b101 ;
1#
#1880000
0#
#1885000
b10 8
15
0:
b111110101 0
b1100111 2
b110 ;
1#
#1890000
0#
#1895000
05
b101 8
b10 ;
b11 6
1#
#1900000
0#
#1905000
b110 8
1:
b101 ;
1#
#1910000
0#
#1915000
15
0:
b10 8
b110 ;
b111111010 0
b10110011 2
1#
#1920000
0#
#1925000
b101 8
05
b100 6
b10 ;
1#
#1930000
0#
#1935000
b110 8
1:
b101 ;
1#
#1940000
0#
#1945000
b10 8
15
0:
b111111101 0
b1011001 2
b110 ;
1#
#1950000
0#
#1955000
05
b101 8
b10 ;
b101 6
1#
#1960000
0#
#1965000
b110 8
1:
b101 ;
1#
#1970000
0#
#1975000
15
0:
b10 8
b110 ;
b111111110 0
b10101100 2
1#
#1980000
0#
#1985000
b11 8
05
b110 6
b10 ;
1#
#1990000
0#
#1995000
b101 8
14
b11 ;
1#
#2000000
0#
#2005000
b110 8
1:
04
b1010011 0
b101 ;
b10 )
1#
#2010000
0#
#2015000
15
0:
b10 8
b110 ;
b101001 0
b11010110 2
03
1#
#2020000
0#
#2025000
b101 8
05
b111 6
b10 ;
1#
#2030000
0#
#2035000
b110 8
1:
b101 ;
1#
#2040000
0#
#2045000
b111 8
15
0:
b10100 0
b11101011 2
b110 ;
1#
#2050000
0#
#2055000
1"
05
b0 8
b111 ;
b1000 6
b1010011101011 !
b1010011101011 9
1#
#2060000
0#
#2065000
0"
b0 ;
b111 -
b101001001011 $
b11111 >
b111 +
1#
#2070000
0#
#2075000
b1 8
1(
b11111 &
b11111 /
1#
#2080000
0#
#2085000
b10 8
17
0(
b1 ;
1#
#2090000
0#
#2095000
07
b100 8
b10 ;
b0 !
b0 9
b0 6
b11111 2
b0 0
1#
#2100000
0#
#2105000
b101 8
1<
b100 ;
1#
#2110000
0#
#2115000
b110 8
1:
0<
b1000 ,
b101 ;
b110101011 0
1#
#2120000
0#
#2125000
b10 8
15
0:
b111010101 0
b10001111 2
13
b110 ;
1#
#2130000
0#
#2135000
05
b101 8
b10 ;
b1 6
1#
#2140000
0#
#2145000
b110 8
1:
b101 ;
1#
#2150000
0#
#2155000
15
0:
b10 8
b110 ;
b111101010 0
b11000111 2
1#
#2160000
0#
#2165000
b101 8
05
b10 6
b10 ;
1#
#2170000
0#
#2175000
b110 8
1:
b101 ;
1#
#2180000
0#
#2185000
b10 8
15
0:
b111110101 0
b1100011 2
b110 ;
1#
#2190000
0#
#2195000
05
b101 8
b10 ;
b11 6
1#
#2200000
0#
#2205000
b110 8
1:
b101 ;
1#
#2210000
0#
#2215000
15
0:
b10 8
b110 ;
b111111010 0
b10110001 2
1#
#2220000
0#
#2225000
b101 8
05
b100 6
b10 ;
1#
#2230000
0#
#2235000
b110 8
1:
b101 ;
1#
#2240000
0#
#2245000
b10 8
15
0:
b111111101 0
b1011000 2
b110 ;
1#
#2250000
0#
#2255000
05
b11 8
b10 ;
b101 6
1#
#2260000
0#
#2265000
b101 8
14
b11 ;
1#
#2270000
0#
#2275000
b110 8
1:
04
b11 )
b101 ;
b1010010 0
1#
#2280000
0#
#2285000
b10 8
15
0:
b101001 0
b101100 2
03
b110 ;
1#
#2290000
0#
#2295000
05
b101 8
b10 ;
b110 6
1#
#2300000
0#
#2305000
b110 8
1:
b101 ;
1#
#2310000
0#
#2315000
15
0:
b10 8
b110 ;
b10100 0
b10010110 2
1#
#2320000
0#
#2325000
b101 8
05
b111 6
b10 ;
1#
#2330000
0#
#2335000
b110 8
1:
b101 ;
1#
#2340000
0#
#2345000
b111 8
15
0:
b1010 0
b1001011 2
b110 ;
1#
#2350000
0#
#2355000
1"
05
b0 8
b111 ;
b1000 6
b101001001011 !
b101001001011 9
1#
#2360000
0#
#2365000
0"
b0 ;
b1000 -
b10011111011 $
b1111 >
b1000 +
1#
#2370000
0#
#2375000
b1 8
1(
b1111 &
b1111 /
1#
#2380000
0#
#2385000
b10 8
17
0(
b1 ;
1#
#2390000
0#
#2395000
07
b100 8
b10 ;
b0 !
b0 9
b0 6
b1111 2
b0 0
1#
#2400000
0#
#2405000
b101 8
1<
b100 ;
1#
#2410000
0#
#2415000
b110 8
1:
0<
b1001 ,
b101 ;
b110101011 0
1#
#2420000
0#
#2425000
b10 8
15
0:
b111010101 0
b10000111 2
13
b110 ;
1#
#2430000
0#
#2435000
05
b101 8
b10 ;
b1 6
1#
#2440000
0#
#2445000
b110 8
1:
b101 ;
1#
#2450000
0#
#2455000
15
0:
b10 8
b110 ;
b111101010 0
b11000011 2
1#
#2460000
0#
#2465000
b101 8
05
b10 6
b10 ;
1#
#2470000
0#
#2475000
b110 8
1:
b101 ;
1#
#2480000
0#
#2485000
b10 8
15
0:
b111110101 0
b1100001 2
b110 ;
1#
#2490000
0#
#2495000
05
b101 8
b10 ;
b11 6
1#
#2500000
0#
#2505000
b110 8
1:
b101 ;
1#
#2510000
0#
#2515000
15
0:
b10 8
b110 ;
b111111010 0
b10110000 2
1#
#2520000
0#
#2525000
b11 8
05
b100 6
b10 ;
1#
#2530000
0#
#2535000
b101 8
14
b11 ;
1#
#2540000
0#
#2545000
b110 8
1:
04
b1001111 0
b101 ;
b100 )
1#
#2550000
0#
#2555000
15
0:
b10 8
b110 ;
b100111 0
b11011000 2
03
1#
#2560000
0#
#2565000
b101 8
05
b101 6
b10 ;
1#
#2570000
0#
#2575000
b110 8
1:
b101 ;
1#
#2580000
0#
#2585000
b10 8
15
0:
b10011 0
b11101100 2
b110 ;
1#
#2590000
0#
#2595000
05
b101 8
b10 ;
b110 6
1#
#2600000
0#
#2605000
b110 8
1:
b101 ;
1#
#2610000
0#
#2615000
15
0:
b10 8
b110 ;
b1001 0
b11110110 2
1#
#2620000
0#
#2625000
b101 8
05
b111 6
b10 ;
1#
#2630000
0#
#2635000
b110 8
1:
b101 ;
1#
#2640000
0#
#2645000
b111 8
15
0:
b100 0
b11111011 2
b110 ;
1#
#2650000
0#
#2655000
1"
05
b0 8
b111 ;
b1000 6
b10011111011 !
b10011111011 9
1#
#2660000
0#
#2665000
0"
b0 ;
b1001 -
b1001010011 $
b111 >
b1001 +
1#
#2670000
0#
#2675000
b1 8
1(
b111 &
b111 /
1#
#2680000
0#
#2685000
b10 8
17
0(
b1 ;
1#
#2690000
0#
#2695000
07
b100 8
b10 ;
b0 !
b0 9
b0 6
b111 2
b0 0
1#
#2700000
0#
#2705000
b101 8
1<
b100 ;
1#
#2710000
0#
#2715000
b110 8
1:
0<
b1010 ,
b101 ;
b110101011 0
1#
#2720000
0#
#2725000
b10 8
15
0:
b111010101 0
b10000011 2
13
b110 ;
1#
#2730000
0#
#2735000
05
b101 8
b10 ;
b1 6
1#
#2740000
0#
#2745000
b110 8
1:
b101 ;
1#
#2750000
0#
#2755000
15
0:
b10 8
b110 ;
b111101010 0
b11000001 2
1#
#2760000
0#
#2765000
b101 8
05
b10 6
b10 ;
1#
#2770000
0#
#2775000
b110 8
1:
b101 ;
1#
#2780000
0#
#2785000
b10 8
15
0:
b111110101 0
b1100000 2
b110 ;
1#
#2790000
0#
#2795000
05
b11 8
b10 ;
b11 6
1#
#2800000
0#
#2805000
b101 8
14
b11 ;
1#
#2810000
0#
#2815000
b110 8
1:
04
b101 )
b101 ;
b1001010 0
1#
#2820000
0#
#2825000
b10 8
15
0:
b100101 0
b110000 2
03
b110 ;
1#
#2830000
0#
#2835000
05
b101 8
b10 ;
b100 6
1#
#2840000
0#
#2845000
b110 8
1:
b101 ;
1#
#2850000
0#
#2855000
15
0:
b10 8
b110 ;
b10010 0
b10011000 2
1#
#2860000
0#
